<?xml version="1.0"?>
<gsmrs version="2.0" sport="soccer" lang="en" last_generated="2011-12-05 21:08:19"><method method_id="7" name="get_teams"><parameter name="detailed" value="no"/><parameter name="id" value="6487"/><parameter name="lang" value="en"/><parameter name="type" value="season"/></method><team team_id="1192" type="club" soccertype="default" teamtype="default" club_name="Bray Wanderers"/><team team_id="1194" type="club" soccertype="default" teamtype="default" club_name="Finn Harps"/><team team_id="5339" type="club" soccertype="women" teamtype="women" club_name="Derry City"/><team team_id="8200" type="club" soccertype="default" teamtype="default" club_name="Limerick"/></gsmrs>
