<?xml version="1.0"?>
<gsmrs version="2.0" sport="soccer" lang="en" last_generated="2011-12-05 20:55:20"><method method_id="7" name="get_teams"><parameter name="detailed" value="no"/><parameter name="id" value="5765"/><parameter name="lang" value="en"/><parameter name="type" value="season"/></method><team team_id="4345" type="national" soccertype="default" teamtype="default" club_name="Albania U21"/><team team_id="4346" type="national" soccertype="default" teamtype="default" club_name="Armenia U21"/><team team_id="4347" type="national" soccertype="default" teamtype="default" club_name="Austria U21"/><team team_id="4348" type="national" soccertype="default" teamtype="default" club_name="Azerbaijan U21"/><team team_id="4349" type="national" soccertype="default" teamtype="default" club_name="Belarus U21"/><team team_id="4350" type="national" soccertype="default" teamtype="default" club_name="Belgium U21"/><team team_id="4351" type="national" soccertype="default" teamtype="default" club_name="Bosnia-Herzegovina U21"/><team team_id="4352" type="national" soccertype="default" teamtype="default" club_name="Bulgaria U21"/><team team_id="4353" type="national" soccertype="default" teamtype="default" club_name="Croatia U21"/><team team_id="4354" type="national" soccertype="default" teamtype="default" club_name="Cyprus U21"/><team team_id="4355" type="national" soccertype="default" teamtype="default" club_name="Czech Republic U21"/><team team_id="4356" type="national" soccertype="default" teamtype="default" club_name="Denmark U21"/><team team_id="4357" type="national" soccertype="default" teamtype="default" club_name="England U21"/><team team_id="4358" type="national" soccertype="default" teamtype="default" club_name="Estonia U21"/><team team_id="4359" type="national" soccertype="default" teamtype="default" club_name="Finland U21"/><team team_id="4360" type="national" soccertype="default" teamtype="default" club_name="France U21"/><team team_id="4361" type="national" soccertype="default" teamtype="default" club_name="Georgia U21"/><team team_id="4362" type="national" soccertype="default" teamtype="default" club_name="Germany U21"/><team team_id="4363" type="national" soccertype="default" teamtype="default" club_name="Greece U21"/><team team_id="4364" type="national" soccertype="default" teamtype="default" club_name="Hungary U21"/><team team_id="4365" type="national" soccertype="default" teamtype="default" club_name="Iceland U21"/><team team_id="4366" type="national" soccertype="default" teamtype="default" club_name="Ireland Rep U21"/><team team_id="4368" type="national" soccertype="default" teamtype="default" club_name="Italy U21"/><team team_id="4369" type="national" soccertype="default" teamtype="default" club_name="Kazakhstan U21"/><team team_id="4370" type="national" soccertype="default" teamtype="default" club_name="Latvia U21"/><team team_id="4371" type="national" soccertype="default" teamtype="default" club_name="Lithuania U21"/><team team_id="4372" type="national" soccertype="default" teamtype="default" club_name="Luxembourg U21"/><team team_id="4373" type="national" soccertype="default" teamtype="default" club_name="Macedonia FYR U21"/><team team_id="4374" type="national" soccertype="default" teamtype="default" club_name="Malta U21"/><team team_id="4375" type="national" soccertype="default" teamtype="default" club_name="Moldova U21"/><team team_id="4376" type="national" soccertype="default" teamtype="default" club_name="Netherlands U21"/><team team_id="4377" type="national" soccertype="default" teamtype="default" club_name="Norway U21"/><team team_id="4378" type="national" soccertype="default" teamtype="default" club_name="Poland U21"/><team team_id="4379" type="national" soccertype="default" teamtype="default" club_name="Portugal U21"/><team team_id="4380" type="national" soccertype="default" teamtype="default" club_name="Romania U21"/><team team_id="4381" type="national" soccertype="default" teamtype="default" club_name="Russia U21"/><team team_id="4382" type="national" soccertype="default" teamtype="default" club_name="San Marino U21"/><team team_id="4383" type="national" soccertype="default" teamtype="default" club_name="Scotland U21"/><team team_id="4385" type="national" soccertype="default" teamtype="default" club_name="Slovakia U21"/><team team_id="4386" type="national" soccertype="default" teamtype="default" club_name="Slovenia U21"/><team team_id="4387" type="national" soccertype="default" teamtype="default" club_name="Spain U21"/><team team_id="4388" type="national" soccertype="default" teamtype="default" club_name="Sweden U21"/><team team_id="4389" type="national" soccertype="default" teamtype="default" club_name="Switzerland U21"/><team team_id="4390" type="national" soccertype="default" teamtype="default" club_name="Turkey U21"/><team team_id="4391" type="national" soccertype="default" teamtype="default" club_name="Ukraine U21"/><team team_id="4392" type="national" soccertype="default" teamtype="default" club_name="Wales U21"/><team team_id="6950" type="national" soccertype="default" teamtype="default" club_name="Andorra U21"/><team team_id="6951" type="national" soccertype="default" teamtype="default" club_name="Liechtenstein U21"/><team team_id="6952" type="national" soccertype="default" teamtype="default" club_name="North. Ireland U21"/><team team_id="6953" type="national" soccertype="default" teamtype="default" club_name="Serbia U21"/><team team_id="9993" type="national" soccertype="default" teamtype="default" club_name="Faroe Islands U21"/><team team_id="9994" type="national" soccertype="default" teamtype="default" club_name="Montenegro U21"/></gsmrs>
