<?xml version="1.0"?>
<gsmrs version="2.0" sport="soccer" lang="en" last_generated="2011-12-05 18:42:12"><method method_id="7" name="get_teams"><parameter name="detailed" value="no"/><parameter name="id" value="6472"/><parameter name="lang" value="en"/><parameter name="type" value="season"/></method><team team_id="301" type="club" soccertype="default" teamtype="default" club_name="Ponte Preta"/><team team_id="302" type="club" soccertype="default" teamtype="default" club_name="S&#xE3;o Paulo"/><team team_id="310" type="club" soccertype="default" teamtype="default" club_name="Palmeiras"/><team team_id="311" type="club" soccertype="default" teamtype="default" club_name="S&#xE3;o Caetano"/><team team_id="316" type="club" soccertype="default" teamtype="default" club_name="Guarani"/><team team_id="319" type="club" soccertype="default" teamtype="default" club_name="Santos"/><team team_id="320" type="club" soccertype="default" teamtype="default" club_name="Corinthians"/><team team_id="331" type="club" soccertype="default" teamtype="default" club_name="Paulista"/><team team_id="335" type="club" soccertype="default" teamtype="default" club_name="Portuguesa"/><team team_id="340" type="club" soccertype="default" teamtype="default" club_name="Ituano"/><team team_id="342" type="club" soccertype="default" teamtype="default" club_name="Mogi Mirim"/><team team_id="2827" type="club" soccertype="default" teamtype="default" club_name="Bragantino"/><team team_id="2828" type="club" soccertype="default" teamtype="default" club_name="Botafogo SP"/><team team_id="2830" type="club" soccertype="default" teamtype="default" club_name="XV de Piracicaba"/><team team_id="7882" type="club" soccertype="default" teamtype="default" club_name="Americana"/><team team_id="10164" type="club" soccertype="default" teamtype="default" club_name="Mirassol"/><team team_id="10307" type="club" soccertype="default" teamtype="default" club_name="Comercial"/><team team_id="10309" type="club" soccertype="default" teamtype="default" club_name="Oeste"/><team team_id="10316" type="club" soccertype="default" teamtype="default" club_name="Catanduvense"/><team team_id="10898" type="club" soccertype="default" teamtype="default" club_name="Linense"/></gsmrs>
